swissarmy/__init__.py
swissarmy/apps.py
swissarmy/defaults.py
swissarmy/mixins/models/__init__.py
swissarmy/mixins/models/uuid_model.py
swissarmy/mixins/settings/__init__.py
swissarmy/mixins/settings/default_settings.py
django_swissarmy-0.1.1.dist-info/LICENSE
django_swissarmy-0.1.1.dist-info/METADATA
django_swissarmy-0.1.1.dist-info/WHEEL
django_swissarmy-0.1.1.dist-info/top_level.txt
django_swissarmy-0.1.1.dist-info/RECORD
